vbd/VBD.py
vbd/__init__.py
vbd-0.0.2.data/scripts/fantasy-draft
vbd-0.0.2.dist-info/METADATA
vbd-0.0.2.dist-info/RECORD
vbd-0.0.2.dist-info/WHEEL
vbd-0.0.2.dist-info/top_level.txt
