Metadata-Version: 2.1
Name: vbd
Version: 0.0.2
Summary: A package for value based drafting
Home-page: https://github.com/famendola1/VBD-Package
Author: Fabio Amendola
Author-email: fabio.amendola20@gmail.com
License: UNKNOWN
Platform: UNKNOWN
Classifier: Programming Language :: Python :: 3
Classifier: License :: OSI Approved :: MIT License
Classifier: Operating System :: OS Independent
